evolutionsimulator/__init__.py
evolutionsimulator/__main__.py
evolutionsimulator/animals.py
evolutionsimulator/automatic_testing.py
evolutionsimulator/data_analyzer.py
evolutionsimulator/data_grouper.py
evolutionsimulator/environment.py
evolutionsimulator/interactive.py
evolutionsimulator/interactive_graphics.py
evolutionsimulator/configs/automatic_testing/mice_and_owls.ini
evolutionsimulator/configs/automatic_testing/my_config.ini
evolutionsimulator/configs/automatic_testing/only_mice.ini
evolutionsimulator/configs/automatic_testing/run_16_07_20.ini
evolutionsimulator/configs/interactive/hello.ini
evolutionsimulator/configs/interactive/mice_and_owls.ini
evolutionsimulator/configs/interactive/only_mice.ini
evolutionsimulator/configs/interactive/smaller_mice_and_owls.ini
evolutionsimulator/images/mouse.jpg
evolutionsimulator/images/mouse_jpg.pgm
evolutionsimulator/images/mouse_resized.pgm
evolutionsimulator/images/owl.jpg
evolutionsimulator/images/owl.png
evolutionsimulator/images/owl_gif.gif
evolutionsimulator/images/owl_image_50.GIF
evolutionsimulator/resources/welcome_text.html
evolutionsimulator/results/automatic_testing.csv
evolutionsimulator/results/empty
evolutionsimulator/results/grouped_results.csv
evolutionsimulator-0.1.20.dist-info/METADATA
evolutionsimulator-0.1.20.dist-info/WHEEL
evolutionsimulator-0.1.20.dist-info/entry_points.txt
evolutionsimulator-0.1.20.dist-info/top_level.txt
evolutionsimulator-0.1.20.dist-info/RECORD
