Metadata-Version: 2.1
Name: evolutionsimulator
Version: 0.1.20
Summary: Simulate evolution
Home-page: https://github.com/koefoeden/Evolution-Simulator
Author: koefoeden
Author-email: koefoeden@gmail.com
License: MIT
Platform: UNKNOWN
Classifier: License :: OSI Approved :: MIT License
Classifier: Programming Language :: Python :: 3.7
Requires-Dist: colorama (>=0.4.3)
Requires-Dist: cursor (>=1.3.4)
Requires-Dist: keyboard (>=0.13.4)
Requires-Dist: numpy (>=1.18.1)
Requires-Dist: pandas (>=1.0.1)
Requires-Dist: python-dateutil (>=2.8.1)
Requires-Dist: pytz (>=2019.3)
Requires-Dist: six (>=1.14.0)
Requires-Dist: termcolor (>=1.1.0)
Requires-Dist: tkinterhtml (>=0.7)
Requires-Dist: tk-html-widgets
